[{"time":1648318502,"crops":["Carrot","Mushroom","Pumpkin"]},{"time":1648322102,"crops":["Melon","Nether Wart","Wheat"]},{"time":1648325702,"crops":["Cactus","Cocoa Beans","Potato"]},{"time":1648329302,"crops":["Cactus","Potato","Wheat"]},{"time":1648332902,"crops":["Cocoa Beans","Mushroom","Nether Wart"]},{"time":1648336502,"crops":["Carrot","Melon","Sugar Cane"]},{"time":1648340102,"crops":["Carrot","Nether Wart","Pumpkin"]},{"time":1648343702,"crops":["Mushroom","Potato","Sugar Cane"]},{"time":1648347302,"crops":["Cocoa Beans","Melon","Wheat"]},{"time":1648350902,"crops":["Mushroom","Nether Wart","Wheat"]},{"time":1648354502,"crops":["Cactus","Melon","Pumpkin"]},{"time":1648358102,"crops":["Cocoa Beans","Potato","Sugar Cane"]},{"time":1648361702,"crops":["Cactus","Melon","Potato"]},{"time":1648365302,"crops":["Carrot","Mushroom","Pumpkin"]},{"time":1648368902,"crops":["Nether Wart","Sugar Cane","Wheat"]},{"time":1648372502,"crops":["Potato","Pumpkin","Sugar Cane"]},{"time":1648376102,"crops":["Cactus","Cocoa Beans","Wheat"]},{"time":1648379702,"crops":["Carrot","Melon","Nether Wart"]},{"time":1648383302,"crops":["Carrot","Sugar Cane","Wheat"]},{"time":1648386902,"crops":["Cocoa Beans","Melon","Pumpkin"]},{"time":1648390502,"crops":["Cactus","Mushroom","Potato"]},{"time":1648394102,"crops":["Mushroom","Pumpkin","Wheat"]},{"time":1648397702,"crops":["Cactus","Carrot","Cocoa Beans"]},{"time":1648404902,"crops":["Pumpkin","Sugar Cane","Wheat"]},{"time":1648408502,"crops":["Cactus","Nether Wart","Potato"]},{"time":1648412102,"crops":["Carrot","Melon","Mushroom"]},{"time":1648415702,"crops":["Cactus","Cocoa Beans","Nether Wart"]},{"time":1648419302,"crops":["Carrot","Melon","Sugar Cane"]},{"time":1648422902,"crops":["Potato","Pumpkin","Wheat"]},{"time":1648426502,"crops":["Carrot","Melon","Sugar Cane"]},{"time":1648430102,"crops":["Cocoa Beans","Mushroom","Wheat"]},{"time":1648433702,"crops":["Cactus","Potato","Pumpkin"]},{"time":1648437302,"crops":["Cactus","Cocoa Beans","Melon"]},{"time":1648440902,"crops":["Carrot","Mushroom","Potato"]},{"time":1648444502,"crops":["Nether Wart","Sugar Cane","Wheat"]},{"time":1648448102,"crops":["Cocoa Beans","Sugar Cane","Wheat"]},{"time":1648451702,"crops":["Nether Wart","Potato","Pumpkin"]},{"time":1648455302,"crops":["Cactus","Melon","Mushroom"]},{"time":1648458902,"crops":["Cactus","Nether Wart","Potato"]},{"time":1648462502,"crops":["Carrot","Melon","Mushroom"]},{"time":1648466102,"crops":["Cocoa Beans","Pumpkin","Wheat"]},{"time":1648469702,"crops":["Melon","Mushroom","Sugar Cane"]},{"time":1648473302,"crops":["Cactus","Carrot","Potato"]},{"time":1648476902,"crops":["Cocoa Beans","Nether Wart","Pumpkin"]},{"time":1648480502,"crops":["Carrot","Cocoa Beans","Potato"]},{"time":1648484102,"crops":["Melon","Pumpkin","Sugar Cane"]},{"time":1648487702,"crops":["Mushroom","Nether Wart","Wheat"]},{"time":1648491302,"crops":["Carrot","Potato","Sugar Cane"]},{"time":1648494902,"crops":["Cactus","Cocoa Beans","Wheat"]},{"time":1648498502,"crops":["Melon","Mushroom","Nether Wart"]},{"time":1648502102,"crops":["Cactus","Melon","Wheat"]},{"time":1648505702,"crops":["Carrot","Nether Wart","Potato"]},{"time":1648509302,"crops":["Mushroom","Pumpkin","Sugar Cane"]},{"time":1648512902,"crops":["Cactus","Cocoa Beans","Nether Wart"]},{"time":1648516502,"crops":["Melon","Mushroom","Wheat"]},{"time":1648520102,"crops":["Carrot","Pumpkin","Sugar Cane"]},{"time":1648523702,"crops":["Melon","Sugar Cane","Wheat"]},{"time":1648527302,"crops":["Carrot","Mushroom","Pumpkin"]},{"time":1648530902,"crops":["Cactus","Cocoa Beans","Potato"]},{"time":1648534502,"crops":["Potato","Sugar Cane","Wheat"]},{"time":1648538102,"crops":["Cocoa Beans","Mushroom","Pumpkin"]},{"time":1648541702,"crops":["Carrot","Melon","Nether Wart"]},{"time":1648545302,"crops":["Cactus","Cocoa Beans","Wheat"]},{"time":1648548902,"crops":["Melon","Mushroom","Nether Wart"]},{"time":1648552502,"crops":["Potato","Pumpkin","Sugar Cane"]},{"time":1648556102,"crops":["Cocoa Beans","Mushroom","Wheat"]},{"time":1648559702,"crops":["Nether Wart","Potato","Sugar Cane"]},{"time":1648563302,"crops":["Cactus","Carrot","Pumpkin"]},{"time":1648566902,"crops":["Mushroom","Potato","Pumpkin"]},{"time":1648570502,"crops":["Carrot","Melon","Sugar Cane"]},{"time":1648574102,"crops":["Cactus","Cocoa Beans","Nether Wart"]},{"time":1648577702,"crops":["Cocoa Beans","Melon","Potato"]},{"time":1648581302,"crops":["Carrot","Nether Wart","Sugar Cane"]},{"time":1648584902,"crops":["Cactus","Mushroom","Pumpkin"]},{"time":1648588502,"crops":["Cocoa Beans","Mushroom","Nether Wart"]},{"time":1648592102,"crops":["Potato","Pumpkin","Wheat"]},{"time":1648595702,"crops":["Carrot","Melon","Sugar Cane"]},{"time":1648599302,"crops":["Potato","Pumpkin","Sugar Cane"]},{"time":1648602902,"crops":["Melon","Mushroom","Nether Wart"]},{"time":1648606502,"crops":["Cactus","Carrot","Wheat"]},{"time":1648610102,"crops":["Cactus","Pumpkin","Sugar Cane"]},{"time":1648613702,"crops":["Cocoa Beans","Melon","Nether Wart"]},{"time":1648617302,"crops":["Carrot","Potato","Wheat"]},{"time":1648620902,"crops":["Carrot","Cocoa Beans","Pumpkin"]},{"time":1648624502,"crops":["Melon","Nether Wart","Sugar Cane"]},{"time":1648628102,"crops":["Cactus","Mushroom","Wheat"]},{"time":1648631702,"crops":["Cactus","Cocoa Beans","Sugar Cane"]},{"time":1648635302,"crops":["Mushroom","Pumpkin","Wheat"]},{"time":1648638902,"crops":["Carrot","Melon","Potato"]},{"time":1648642502,"crops":["Mushroom","Sugar Cane","Wheat"]},{"time":1648646102,"crops":["Melon","Potato","Pumpkin"]},{"time":1648649702,"crops":["Cactus","Cocoa Beans","Nether Wart"]},{"time":1648653302,"crops":["Melon","Mushroom","Potato"]},{"time":1648656902,"crops":["Carrot","Nether Wart","Pumpkin"]},{"time":1648660502,"crops":["Cactus","Cocoa Beans","Wheat"]}]